sails/__init__.py
sails/_docstring_utils.py
sails/anam.py
sails/circular_plots.py
sails/diags.py
sails/modal.py
sails/modelfit.py
sails/modelvalidation.py
sails/mvar_metrics.py
sails/orthogonalise.py
sails/permute.py
sails/plotting.py
sails/simulate.py
sails/stats.py
sails/stft.py
sails/support.py
sails/tutorial_utils.py
sails/utils.py
sails/wavelet.py
sails/support/aal_cortical_plotting_groups.csv
sails/support/aal_cortical_plotting_regions.csv
sails/tests/__init__.py
sails/tests/test_diags.py
sails/tests/test_docstrings.py
sails/tests/test_modal.py
sails/tests/test_modelfit.py
sails/tests/test_stats.py
sails/tests/test_stft.py
sails/tests/test_utils.py
sails/tests/test_wavelet.py
sails-1.7.0.dist-info/licenses/LICENSE.txt
sails-1.7.0.dist-info/METADATA
sails-1.7.0.dist-info/WHEEL
sails-1.7.0.dist-info/top_level.txt
sails-1.7.0.dist-info/RECORD
