Metadata-Version: 2.4
Name: sails
Version: 1.7.0
Summary: Spectral Analysis In Linear Systems
Author: Andrew Quinn <andrew.quinn@psych.ox.ac.uk>, Mark Hymers <mark.hymers@ynic.york.ac.uk>
Author-email: sails-devel@ynic.york.ac.uk
License: GPL-2+
Keywords: multivariate autoregressive models spectral
Classifier: Development Status :: 4 - Beta
Classifier: Intended Audience :: Science/Research
Classifier: Topic :: Scientific/Engineering :: Bio-Informatics
Classifier: Topic :: Scientific/Engineering :: Information Analysis
Classifier: Topic :: Scientific/Engineering :: Mathematics
Classifier: License :: OSI Approved :: GNU General Public License v2 or later (GPLv2+)
Classifier: Programming Language :: Python :: 3
Classifier: Programming Language :: Python :: 3.9
Classifier: Programming Language :: Python :: 3.10
Classifier: Programming Language :: Python :: 3.11
Classifier: Programming Language :: Python :: 3.12
Classifier: Programming Language :: Python :: 3.13
License-File: LICENSE.txt
Requires-Dist: numpy
Requires-Dist: scipy
Requires-Dist: matplotlib
Requires-Dist: h5py
Requires-Dist: scikit-learn
Requires-Dist: importlib-metadata<5.0.0
Requires-Dist: numpydoc
Provides-Extra: full
Requires-Dist: sphinx_rtd_theme; extra == "full"
Requires-Dist: pydata-sphinx-theme; extra == "full"
Requires-Dist: setuptools; extra == "full"
Requires-Dist: scikit-learn; extra == "full"
Requires-Dist: sphinx; extra == "full"
Requires-Dist: flake8; extra == "full"
Requires-Dist: pytest; extra == "full"
Requires-Dist: pytest-cov; extra == "full"
Requires-Dist: coverage; extra == "full"
Requires-Dist: codespell; extra == "full"
Requires-Dist: numpydoc; extra == "full"
Dynamic: author
Dynamic: author-email
Dynamic: classifier
Dynamic: description
Dynamic: description-content-type
Dynamic: keywords
Dynamic: license
Dynamic: license-file
Dynamic: provides-extra
Dynamic: requires-dist
Dynamic: summary
